naru/__init__.py
naru/modules.py
naru-0.0.1.dist-info/METADATA
naru-0.0.1.dist-info/WHEEL
naru-0.0.1.dist-info/top_level.txt
naru-0.0.1.dist-info/RECORD
