Metadata-Version: 2.1
Name: naru
Version: 0.0.1
Summary: PYPI tutorial package creation written by TeddyNote
Home-page: https://github.com/teddylee777/teddynote
Author: psw109
Author-email: psw109@gmail.com
Keywords: teddynote,teddylee777,python datasets,python tutorial,pypi
Classifier: Programming Language :: Python :: 3.6
Classifier: Programming Language :: Python :: 3.7
Classifier: Programming Language :: Python :: 3.8
Classifier: Programming Language :: Python :: 3.9
Requires-Python: >=3.6
Requires-Dist: tqdm
Requires-Dist: pandas
Requires-Dist: scikit-learn
